reqstool_python_decorators/__init__.py
reqstool_python_decorators/decorators/decorators.py
reqstool_python_decorators/processors/__init__.py
reqstool_python_decorators/processors/decorator_processor.py
reqstool_python_decorators-0.0.9.dist-info/METADATA
reqstool_python_decorators-0.0.9.dist-info/WHEEL
reqstool_python_decorators-0.0.9.dist-info/licenses/LICENSE
reqstool_python_decorators-0.0.9.dist-info/RECORD
