Metadata-Version: 2.4
Name: reqstool-python-decorators
Version: 0.0.9
Summary: Reqstool Python Decorators
Project-URL: Source, https://github.com/Luftfartsverket/reqstool-python-decorators.git
Author-email: LFV SYSDEV <sysdev@lfv.com>
License-File: LICENSE
Classifier: Development Status :: 4 - Beta
Classifier: License :: OSI Approved :: MIT License
Classifier: Operating System :: OS Independent
Classifier: Programming Language :: Python :: 3
Requires-Python: >=3.10
Requires-Dist: ruamel-yaml>=0.18.5
